{
  "engine": "hymeko_nagare",
  "comparison": "entropy_pool_local_vs_backprop_like_holonomy",
  "n_train": 192,
  "n_test": 96,
  "n_points": 32,
  "hidden": 24,
  "epochs": 50,
  "rows": [
    {
      "task": "moons",
      "local_acc": 1.000000,
      "local_loss": 0.001513,
      "local_entropy": 0.015819,
      "local_clifford_error": 0.000007,
      "local_median_us_per_sample": 5.598958,
      "local_mean_us_per_sample": 5.424158,
      "local_max_us_per_sample": 28.843750,
      "backprop_acc": 1.000000,
      "backprop_loss": 0.000129,
      "backprop_median_us_per_sample": 135.698958,
      "local_params": 60,
      "backprop_params": 2836
    },
    {
      "task": "spiral",
      "local_acc": 1.000000,
      "local_loss": 0.004486,
      "local_entropy": 0.041033,
      "local_clifford_error": 0.000044,
      "local_median_us_per_sample": 5.929167,
      "local_mean_us_per_sample": 5.954392,
      "local_max_us_per_sample": 7.471875,
      "backprop_acc": 1.000000,
      "backprop_loss": 0.000001,
      "backprop_median_us_per_sample": 130.491667,
      "local_params": 60,
      "backprop_params": 2836
    },
    {
      "task": "xor",
      "local_acc": 1.000000,
      "local_loss": 0.006714,
      "local_entropy": 0.056046,
      "local_clifford_error": 0.000137,
      "local_median_us_per_sample": 6.138542,
      "local_mean_us_per_sample": 6.078611,
      "local_max_us_per_sample": 7.876042,
      "backprop_acc": 1.000000,
      "backprop_loss": 0.000094,
      "backprop_median_us_per_sample": 133.003125,
      "local_params": 60,
      "backprop_params": 2836
    }
  ],
  "stress_rows": [
    {
      "task": "moons",
      "stress": "clean",
      "entropy_gate": "entropy",
      "entropy_acc": 1.000000,
      "entropy_loss": 0.001513,
      "entropy_clifford_error": 0.000007,
      "entropy_median_us_per_sample": 5.770833,
      "constant_gate": "constant",
      "constant_acc": 1.000000,
      "constant_loss": 0.000465,
      "constant_clifford_error": 0.000001,
      "constant_median_us_per_sample": 5.794792,
      "projection_gate": "projection",
      "projection_acc": 1.000000,
      "projection_loss": 0.001327,
      "projection_clifford_error": 0.000008,
      "projection_median_us_per_sample": 6.058333,
      "entropy_params": 60,
      "constant_params": 60,
      "projection_params": 60
    },
    {
      "task": "moons",
      "stress": "noisy",
      "entropy_gate": "entropy",
      "entropy_acc": 1.000000,
      "entropy_loss": 0.001631,
      "entropy_clifford_error": 0.000008,
      "entropy_median_us_per_sample": 6.093750,
      "constant_gate": "constant",
      "constant_acc": 1.000000,
      "constant_loss": 0.000500,
      "constant_clifford_error": 0.000001,
      "constant_median_us_per_sample": 6.010417,
      "projection_gate": "projection",
      "projection_acc": 1.000000,
      "projection_loss": 0.001253,
      "projection_clifford_error": 0.000008,
      "projection_median_us_per_sample": 5.976042,
      "entropy_params": 60,
      "constant_params": 60,
      "projection_params": 60
    },
    {
      "task": "moons",
      "stress": "missing",
      "entropy_gate": "entropy",
      "entropy_acc": 1.000000,
      "entropy_loss": 0.001656,
      "entropy_clifford_error": 0.000009,
      "entropy_median_us_per_sample": 5.551042,
      "constant_gate": "constant",
      "constant_acc": 1.000000,
      "constant_loss": 0.000516,
      "constant_clifford_error": 0.000001,
      "constant_median_us_per_sample": 5.354167,
      "projection_gate": "projection",
      "projection_acc": 1.000000,
      "projection_loss": 0.001421,
      "projection_clifford_error": 0.000009,
      "projection_median_us_per_sample": 5.483333,
      "entropy_params": 60,
      "constant_params": 60,
      "projection_params": 60
    },
    {
      "task": "moons",
      "stress": "fewshot_noisy_missing",
      "entropy_gate": "entropy",
      "entropy_acc": 1.000000,
      "entropy_loss": 0.011536,
      "entropy_clifford_error": 0.000567,
      "entropy_median_us_per_sample": 5.268750,
      "constant_gate": "constant",
      "constant_acc": 1.000000,
      "constant_loss": 0.005352,
      "constant_clifford_error": 0.000165,
      "constant_median_us_per_sample": 5.412500,
      "projection_gate": "projection",
      "projection_acc": 1.000000,
      "projection_loss": 0.020177,
      "projection_clifford_error": 0.005079,
      "projection_median_us_per_sample": 5.209375,
      "entropy_params": 60,
      "constant_params": 60,
      "projection_params": 60
    },
    {
      "task": "spiral",
      "stress": "clean",
      "entropy_gate": "entropy",
      "entropy_acc": 1.000000,
      "entropy_loss": 0.004487,
      "entropy_clifford_error": 0.000044,
      "entropy_median_us_per_sample": 6.032292,
      "constant_gate": "constant",
      "constant_acc": 1.000000,
      "constant_loss": 0.001581,
      "constant_clifford_error": 0.000006,
      "constant_median_us_per_sample": 5.727083,
      "projection_gate": "projection",
      "projection_acc": 1.000000,
      "projection_loss": 0.001676,
      "projection_clifford_error": 0.000006,
      "projection_median_us_per_sample": 6.067708,
      "entropy_params": 60,
      "constant_params": 60,
      "projection_params": 60
    },
    {
      "task": "spiral",
      "stress": "noisy",
      "entropy_gate": "entropy",
      "entropy_acc": 0.989583,
      "entropy_loss": 0.043077,
      "entropy_clifford_error": 0.021268,
      "entropy_median_us_per_sample": 6.069792,
      "constant_gate": "constant",
      "constant_acc": 0.989583,
      "constant_loss": 0.040756,
      "constant_clifford_error": 0.020610,
      "constant_median_us_per_sample": 5.842708,
      "projection_gate": "projection",
      "projection_acc": 0.989583,
      "projection_loss": 0.051638,
      "projection_clifford_error": 0.023133,
      "projection_median_us_per_sample": 6.015625,
      "entropy_params": 60,
      "constant_params": 60,
      "projection_params": 60
    },
    {
      "task": "spiral",
      "stress": "missing",
      "entropy_gate": "entropy",
      "entropy_acc": 1.000000,
      "entropy_loss": 0.015772,
      "entropy_clifford_error": 0.003732,
      "entropy_median_us_per_sample": 5.398958,
      "constant_gate": "constant",
      "constant_acc": 1.000000,
      "constant_loss": 0.011051,
      "constant_clifford_error": 0.002899,
      "constant_median_us_per_sample": 5.528125,
      "projection_gate": "projection",
      "projection_acc": 1.000000,
      "projection_loss": 0.012821,
      "projection_clifford_error": 0.002247,
      "projection_median_us_per_sample": 5.527083,
      "entropy_params": 60,
      "constant_params": 60,
      "projection_params": 60
    },
    {
      "task": "spiral",
      "stress": "fewshot_noisy_missing",
      "entropy_gate": "entropy",
      "entropy_acc": 0.927083,
      "entropy_loss": 0.286730,
      "entropy_clifford_error": 0.151213,
      "entropy_median_us_per_sample": 5.397917,
      "constant_gate": "constant",
      "constant_acc": 0.937500,
      "constant_loss": 0.269849,
      "constant_clifford_error": 0.140570,
      "constant_median_us_per_sample": 5.388542,
      "projection_gate": "projection",
      "projection_acc": 0.906250,
      "projection_loss": 0.324541,
      "projection_clifford_error": 0.181705,
      "projection_median_us_per_sample": 5.421875,
      "entropy_params": 60,
      "constant_params": 60,
      "projection_params": 60
    },
    {
      "task": "xor",
      "stress": "clean",
      "entropy_gate": "entropy",
      "entropy_acc": 1.000000,
      "entropy_loss": 0.006731,
      "entropy_clifford_error": 0.000139,
      "entropy_median_us_per_sample": 6.155208,
      "constant_gate": "constant",
      "constant_acc": 1.000000,
      "constant_loss": 0.002713,
      "constant_clifford_error": 0.000029,
      "constant_median_us_per_sample": 6.103125,
      "projection_gate": "projection",
      "projection_acc": 1.000000,
      "projection_loss": 0.003012,
      "projection_clifford_error": 0.000052,
      "projection_median_us_per_sample": 6.177083,
      "entropy_params": 60,
      "constant_params": 60,
      "projection_params": 60
    },
    {
      "task": "xor",
      "stress": "noisy",
      "entropy_gate": "entropy",
      "entropy_acc": 1.000000,
      "entropy_loss": 0.006969,
      "entropy_clifford_error": 0.000132,
      "entropy_median_us_per_sample": 6.187500,
      "constant_gate": "constant",
      "constant_acc": 1.000000,
      "constant_loss": 0.002783,
      "constant_clifford_error": 0.000024,
      "constant_median_us_per_sample": 6.026042,
      "projection_gate": "projection",
      "projection_acc": 1.000000,
      "projection_loss": 0.003129,
      "projection_clifford_error": 0.000040,
      "projection_median_us_per_sample": 6.098958,
      "entropy_params": 60,
      "constant_params": 60,
      "projection_params": 60
    },
    {
      "task": "xor",
      "stress": "missing",
      "entropy_gate": "entropy",
      "entropy_acc": 1.000000,
      "entropy_loss": 0.008426,
      "entropy_clifford_error": 0.000169,
      "entropy_median_us_per_sample": 5.622917,
      "constant_gate": "constant",
      "constant_acc": 1.000000,
      "constant_loss": 0.003485,
      "constant_clifford_error": 0.000032,
      "constant_median_us_per_sample": 5.538542,
      "projection_gate": "projection",
      "projection_acc": 1.000000,
      "projection_loss": 0.003558,
      "projection_clifford_error": 0.000033,
      "projection_median_us_per_sample": 5.336458,
      "entropy_params": 60,
      "constant_params": 60,
      "projection_params": 60
    },
    {
      "task": "xor",
      "stress": "fewshot_noisy_missing",
      "entropy_gate": "entropy",
      "entropy_acc": 1.000000,
      "entropy_loss": 0.033405,
      "entropy_clifford_error": 0.002493,
      "entropy_median_us_per_sample": 5.187500,
      "constant_gate": "constant",
      "constant_acc": 1.000000,
      "constant_loss": 0.022253,
      "constant_clifford_error": 0.001176,
      "constant_median_us_per_sample": 5.145833,
      "projection_gate": "projection",
      "projection_acc": 1.000000,
      "projection_loss": 0.023323,
      "projection_clifford_error": 0.001326,
      "projection_median_us_per_sample": 5.216667,
      "entropy_params": 60,
      "constant_params": 60,
      "projection_params": 60
    }
  ]
}
